django_safe_migrations/__init__.py
django_safe_migrations/analyzer.py
django_safe_migrations/apps.py
django_safe_migrations/cli.py
django_safe_migrations/conf.py
django_safe_migrations/suppression.py
django_safe_migrations/utils.py
django_safe_migrations/management/__init__.py
django_safe_migrations/management/commands/__init__.py
django_safe_migrations/management/commands/check_migrations.py
django_safe_migrations/reporters/__init__.py
django_safe_migrations/reporters/base.py
django_safe_migrations/reporters/console.py
django_safe_migrations/reporters/github.py
django_safe_migrations/reporters/json_reporter.py
django_safe_migrations/reporters/sarif.py
django_safe_migrations/rules/__init__.py
django_safe_migrations/rules/add_field.py
django_safe_migrations/rules/add_index.py
django_safe_migrations/rules/alter_field.py
django_safe_migrations/rules/base.py
django_safe_migrations/rules/constraints.py
django_safe_migrations/rules/graph.py
django_safe_migrations/rules/naming.py
django_safe_migrations/rules/relations.py
django_safe_migrations/rules/remove_field.py
django_safe_migrations/rules/run_sql.py
django_safe_migrations-0.4.0.dist-info/METADATA
django_safe_migrations-0.4.0.dist-info/WHEEL
django_safe_migrations-0.4.0.dist-info/entry_points.txt
django_safe_migrations-0.4.0.dist-info/licenses/LICENSE
django_safe_migrations-0.4.0.dist-info/RECORD
