Metadata-Version: 2.4
Name: django-safe-migrations
Version: 0.4.0
Summary: Detect unsafe Django migrations before they break production
Project-URL: Homepage, https://github.com/YasserShkeir/django-safe-migrations
Project-URL: Documentation, https://django-safe-migrations.readthedocs.io/
Project-URL: Repository, https://github.com/YasserShkeir/django-safe-migrations
Project-URL: Changelog, https://github.com/YasserShkeir/django-safe-migrations/blob/main/CHANGELOG.md
Project-URL: Funding, https://www.yasser-shkeir.com/donate
Author-email: Yasser Shkeir <shkeiryasser@gmail.com>
License-Expression: MIT
License-File: LICENSE
Keywords: database,django,linter,migrations,postgres,zero-downtime
Classifier: Development Status :: 4 - Beta
Classifier: Framework :: Django
Classifier: Framework :: Django :: 3.2
Classifier: Framework :: Django :: 4.2
Classifier: Framework :: Django :: 5.0
Classifier: Framework :: Django :: 5.1
Classifier: Framework :: Django :: 6.0
Classifier: Intended Audience :: Developers
Classifier: License :: OSI Approved :: MIT License
Classifier: Programming Language :: Python :: 3
Classifier: Programming Language :: Python :: 3.9
Classifier: Programming Language :: Python :: 3.10
Classifier: Programming Language :: Python :: 3.11
Classifier: Programming Language :: Python :: 3.12
Classifier: Programming Language :: Python :: 3.13
Classifier: Topic :: Database
Classifier: Topic :: Software Development :: Quality Assurance
Requires-Python: >=3.9
Requires-Dist: django>=3.2
Provides-Extra: dev
Requires-Dist: bandit>=1.7; extra == 'dev'
Requires-Dist: black>=22.0; extra == 'dev'
Requires-Dist: build>=0.8; extra == 'dev'
Requires-Dist: django-stubs>=4.0; extra == 'dev'
Requires-Dist: flake8-docstrings>=1.7; extra == 'dev'
Requires-Dist: flake8>=5.0; extra == 'dev'
Requires-Dist: isort>=5.0; extra == 'dev'
Requires-Dist: mypy>=1.0; extra == 'dev'
Requires-Dist: pre-commit>=2.20; extra == 'dev'
Requires-Dist: pytest-cov>=4.0; extra == 'dev'
Requires-Dist: pytest-django>=4.5; extra == 'dev'
Requires-Dist: pytest-xdist>=3.0; extra == 'dev'
Requires-Dist: pytest>=7.0; extra == 'dev'
Requires-Dist: twine>=4.0; extra == 'dev'
Provides-Extra: docs
Requires-Dist: mkdocs-material>=9.0; extra == 'docs'
Requires-Dist: mkdocs>=1.4; extra == 'docs'
Requires-Dist: mkdocstrings[python]>=0.20; extra == 'docs'
Provides-Extra: mysql
Requires-Dist: mysqlclient>=2.1; extra == 'mysql'
Provides-Extra: postgres
Requires-Dist: psycopg2-binary>=2.9; extra == 'postgres'
